dmwmclient/__init__.py
dmwmclient/asyncutil.py
dmwmclient/datasvc.py
dmwmclient/dbs.py
dmwmclient/dynamo.py
dmwmclient/mcm.py
dmwmclient/reqmgr.py
dmwmclient/restclient.py
dmwmclient/unified.py
dmwmclient/util.py
dmwmclient/version.py
dmwmclient/cli/__init__.py
dmwmclient/cli/shell.py
dmwmclient/cli/test.py
dmwmclient/cli/unified.py
dmwmclient-0.0.4.dist-info/LICENSE
dmwmclient-0.0.4.dist-info/METADATA
dmwmclient-0.0.4.dist-info/WHEEL
dmwmclient-0.0.4.dist-info/entry_points.txt
dmwmclient-0.0.4.dist-info/top_level.txt
dmwmclient-0.0.4.dist-info/RECORD
