Metadata-Version: 2.1
Name: dmwmclient
Version: 0.0.4
Summary: client and scripts
Home-page: https://github.com/nsmith-/dmwmclient
Maintainer: Nick Smith
Maintainer-email: nick.smith@cern.ch
License: BSD 3-clause
Download-URL: https://github.com/nsmith-/dmwmclient/releases
Platform: UNKNOWN
Classifier: Development Status :: 3 - Alpha
Classifier: Intended Audience :: Science/Research
Classifier: License :: OSI Approved :: BSD License
Classifier: Programming Language :: Python
Classifier: Programming Language :: Python :: 3.6
Classifier: Programming Language :: Python :: 3.7
Classifier: Topic :: Scientific/Engineering :: Physics
Requires-Dist: httpx (==0.12)
Requires-Dist: lxml
Requires-Dist: ipython
Requires-Dist: pandas (>=0.25)
Provides-Extra: dev
Requires-Dist: flake8 ; extra == 'dev'
Requires-Dist: black ; extra == 'dev'
Requires-Dist: pytest-asyncio ; extra == 'dev'
